yubundle/__init__.py
yubundle/package.py
yubundle-0.0.2.dist-info/LICENSE.md
yubundle-0.0.2.dist-info/METADATA
yubundle-0.0.2.dist-info/WHEEL
yubundle-0.0.2.dist-info/top_level.txt
yubundle-0.0.2.dist-info/RECORD
